{
  "job_title": "Ecommerce Account Manager",
  "company": "Code3",
  "experience_level": "mid",
  "required_skills": [
    "Bachelors degree"
  ],
  "education_requirements": "Bachelors degree",
  "salary_range": {
    "min": null,
    "max": null,
    "currency": null
  },
  "compensation_benefits": [
    "Full benefits - 401k with match",
    "generous pension program",
    "thoughtful parental leave and return program",
    "ample pto holidays and holiday closure in december",
    "ongoing learning and development opportunities",
    "commitment to transparent dei practices",
    "convenient snack stocked office spaces in awesome cities"
  ]
}