{
  "job_title": "Sales Associate- FT",
  "company": "Boscov's Department Store",
  "experience_level": "unknown",
  "required_skills": [
    "Prior retail sales experience and/or customer service experience preferred",
    "Excellent written",
    "verbal and interpersonal communication skills",
    "Proficiency with basic math skills",
    "Ability to learn selling skills and to operate a POS register and Telxon"
  ],
  "education_requirements": "",
  "salary_range": {
    "min": null,
    "max": null,
    "currency": null
  },
  "compensation_benefits": [
    "Competitive starting rate",
    "Weekly pay",
    "Comprehensive benefits package including medical/dental",
    "Paid vacations and personal days",
    "Liberal employee discounts",
    "Opportunity for advancement"
  ]
}