{
  "job_title": "Registered Nurse - RN - Senior Care!",
  "company": "Manorcare Health Services",
  "experience_level": "senior",
  "required_skills": [
    "Licensed RN",
    "1 year nursing experience preferred"
  ],
  "education_requirements": "Currently holds a RN (Registered Nurse) license in this state.",
  "salary_range": {
    "min": null,
    "max": null,
    "currency": null
  },
  "compensation_benefits": [
    "Sign-on bonus",
    "shift and weekend premiums",
    "daily pay",
    "comprehensive health coverage",
    "time off",
    "education benefits such as student loan repayment and discounts"
  ]
}