{
  "job_title": "Senior Accountant, Banking (Lakewood)",
  "company": "First Commerce Bank",
  "experience_level": "senior",
  "required_skills": [
    "5+ years experience in banking or finance",
    "Bachelor's degree in accounting",
    "finance or related field",
    "Knowledge of GAAP and financial reporting",
    "Proficiency in accounting",
    "MS Office",
    "communication and organizational skills"
  ],
  "education_requirements": "Bachelor's degree in accounting, finance, business or related field.",
  "salary_range": {
    "min": null,
    "max": null,
    "currency": null
  },
  "compensation_benefits": [
    "Medical",
    "dental and vision insurance",
    "Life insurance",
    "Disability insurance",
    "Paid holidays and PTO",
    "401K matching",
    "HSA contribution",
    "Employee discount program"
  ]
}