{
  "job_title": "Vice President, Product Marketing",
  "company": "Pagaya",
  "experience_level": "executive",
  "required_skills": [
    "5+ years of marketing experience in inbound marketing",
    "demand generation",
    "paid media and/or account-based marketing",
    "BA in communications",
    "journalism",
    "public relations",
    "marketing or related field",
    "Prior experience in growth marketing",
    "Proficient in analyzing data to solve problems",
    "Strong project management and communication skills"
  ],
  "education_requirements": "BA in communications, journalism, public relations, marketing or related field",
  "salary_range": {
    "min": null,
    "max": null,
    "currency": null
  },
  "compensation_benefits": []
}