{
  "job_title": "Vice President Operations Excellence",
  "company": "NiSource",
  "experience_level": "executive",
  "required_skills": [
    "Leadership and management skills",
    "Ability to build relationships across company",
    "Experience with process management and driving continuous improvement",
    "Ability to set and monitor targets for safety",
    "operational excellence and customer satisfaction"
  ],
  "education_requirements": "Bachelor's degree or comparable industry experience.",
  "salary_range": {
    "min": null,
    "max": null,
    "currency": null
  },
  "compensation_benefits": []
}