{
  "job_title": "Sales Associate - Easton T/C",
  "company": "Gap",
  "experience_level": "unknown",
  "required_skills": [
    "Good communication",
    "ability to utilize technology effectively",
    "engage with customers and team",
    "problem solving",
    "focus on continuous improvement and learning",
    "handle customer interactions professionally"
  ],
  "education_requirements": "",
  "salary_range": {
    "min": null,
    "max": null,
    "currency": null
  },
  "compensation_benefits": [
    "Merchandise discount",
    "paid time off",
    "401k with matching",
    "employee stock purchase plan",
    "medical",
    "dental",
    "vision and life insurance"
  ]
}